color_extraction/__init__.py
color_extraction/color_definitions.json
color_extraction/fct_palette_man_RGB.py
color_extraction-0.1a4.dist-info/LICENSE
color_extraction-0.1a4.dist-info/METADATA
color_extraction-0.1a4.dist-info/WHEEL
color_extraction-0.1a4.dist-info/top_level.txt
color_extraction-0.1a4.dist-info/RECORD
